[
  {
    "title": "Kulturkirke for hvem?",
    "excerpt": "23 millioner til fellesskap – men Sofienberg kirke leies ut som lokale.",
    "image": "Kulturhjul/Sofienberg-kulturkirke.PNG",
    "url": "artikler/2025-10-16-kulturkirke-for-hvem.html",
    "date": "2025-10-16"
  },
  {
    "title": "Nobel 2025: László Krasznahorkai",
    "excerpt": "Litteraturpris til en kompromissløs stemme – hvorfor akkurat nå.",
    "image": "Kulturhjul/Nobel-litteratur-2025.PNG",
    "url": "artikler/2025-10-20-nobel-litteratur-2025.html",
    "date": "2025-10-20"
  },
  {
    "title": "History Go: nye ruter i Oslo",
    "excerpt": "Fra Tøyen til Sagene med samlekort og skjulte steder.",
    "image": "Kulturhjul/History-Go-Oslo-ruter.PNG",
    "url": "artikler/2025-10-12-history-go-nye-ruter-oslo.html",
    "date": "2025-10-12"
  },
  {
    "title": "Lesebiblioteket: Høstprogrammet",
    "excerpt": "Åpne lesninger, små foredrag og verksted for unge skribenter.",
    "image": "Kulturhjul/Lesebiblioteket-hostprogram.PNG",
    "url": "artikler/2025-10-10-lesebiblioteket-hostprogram.html",
    "date": "2025-10-10"
  },
  {
    "title": "Grafisk memoar: Majorstua (Blue Master)",
    "excerpt": "Plakatserien som fanger bydelens rytme og røykfrie nostalgi.",
    "image": "Kulturhjul/Grafisk-Memoar-Majorstua.PNG",
    "url": "artikler/2025-10-08-grafisk-memoar-majorstua.html",
    "date": "2025-10-08"
  },
  {
    "title": "Oslo Open Mic: Standup uten diagnose",
    "excerpt": "Observasjoner fra hverdagen – lett, lekent og uten klaging.",
    "image": "Kulturhjul/Standup-Open-Mic.PNG",
    "url": "artikler/2025-10-05-standup-open-mic.html",
    "date": "2025-10-05"
  },
  {
    "title": "Kino: Ny norsk film – «Natt over Bislett»",
    "excerpt": "En bynær fortelling om vennskap, stillhet og små avgjørende valg.",
    "image": "Kulturhjul/Kino-Natt-over-Bislett.PNG",
    "url": "artikler/2025-10-03-kino-natt-over-bislett.html",
    "date": "2025-10-03"
  },
  {
    "title": "Utstilling: Maskin & Menneske",
    "excerpt": "Kunstnere undersøker friksjon mellom algoritmer og blikk.",
    "image": "Kulturhjul/Utstilling-Maskin-og-Menneske.PNG",
    "url": "artikler/2025-10-02-utstilling-maskin-og-menneske.html",
    "date": "2025-10-02"
  },
  {
    "title": "Konsert: Parkliv Sessions",
    "excerpt": "Akustiske kvelder i Sofienberg – små scener, store øyeblikk.",
    "image": "Kulturhjul/Parkliv-Sessions.PNG",
    "url": "artikler/2025-09-28-konsert-parkliv-sessions.html",
    "date": "2025-09-28"
  }
]
